hiws/WhatsappMessenger.py
hiws/__init__.py
hiws/internal/helpers/__init__.py
hiws/internal/helpers/make_request.py
hiws/types/__init__.py
hiws/types/update.py
hiws/types/exceptions/WhatsappApiException.py
hiws/types/exceptions/__init__.py
hiws/types/message/__init__.py
hiws/types/message/contact.py
hiws/types/status/__init__.py
hiws-0.5.2.dist-info/licenses/LICENSE
hiws-0.5.2.dist-info/METADATA
hiws-0.5.2.dist-info/WHEEL
hiws-0.5.2.dist-info/top_level.txt
hiws-0.5.2.dist-info/RECORD
