Metadata-Version: 2.4
Name: hiws
Version: 0.5.2
Summary: A wrapper for WhatsApp's Cloud API
Author-email: Tomas Santana <tomas@cervant.chat>
License: MIT
Project-URL: Homepage, https://github.com/cervant-ai/hiws
Project-URL: Repository, https://github.com/cervant-ai/hiws.git
Project-URL: Issues, https://github.com/cervant-ai/hiws/issues
Keywords: hiws,python,package
Classifier: Development Status :: 3 - Alpha
Classifier: Intended Audience :: Developers
Classifier: Operating System :: OS Independent
Classifier: Programming Language :: Python :: 3
Classifier: Programming Language :: Python :: 3.7
Classifier: Programming Language :: Python :: 3.8
Classifier: Programming Language :: Python :: 3.9
Classifier: Programming Language :: Python :: 3.10
Classifier: Programming Language :: Python :: 3.11
Requires-Python: >=3.9
License-File: LICENSE
Requires-Dist: pydantic>=2.11.7
Requires-Dist: httpx>=0.28.1
Provides-Extra: dev
Requires-Dist: pytest>=6.0; extra == "dev"
Requires-Dist: pytest-asyncio>=0.23; extra == "dev"
Requires-Dist: black>=21.0; extra == "dev"
Requires-Dist: flake8>=3.8.0; extra == "dev"
Requires-Dist: mypy>=0.800; extra == "dev"
Dynamic: license-file
